pdm_multirun-1.1.1.dist-info/METADATA
pdm_multirun-1.1.1.dist-info/WHEEL
pdm_multirun-1.1.1.dist-info/entry_points.txt
pdm_multirun-1.1.1.dist-info/licenses/LICENSE
pdm_multirun/__init__.py
pdm_multirun/debug.py
pdm_multirun/plugin.py
pdm_multirun/py.typed
pdm_multirun-1.1.1.dist-info/RECORD
