Metadata-Version: 2.1
Name: pdm-multirun
Version: 1.1.1
Summary: A PDM plugin to run a command on multiple Python versions.
Author-Email: =?utf-8?q?Timoth=C3=A9e_Mazzucotelli?= <pawamoy@pm.me>
License: ISC
Classifier: Development Status :: 4 - Beta
Classifier: Intended Audience :: Developers
Classifier: Programming Language :: Python
Classifier: Programming Language :: Python :: 3
Classifier: Programming Language :: Python :: 3 :: Only
Classifier: Programming Language :: Python :: 3.8
Classifier: Programming Language :: Python :: 3.9
Classifier: Programming Language :: Python :: 3.10
Classifier: Programming Language :: Python :: 3.11
Classifier: Programming Language :: Python :: 3.12
Classifier: Topic :: Documentation
Classifier: Topic :: Software Development
Classifier: Topic :: Utilities
Classifier: Typing :: Typed
Project-URL: Homepage, https://pawamoy.github.io/pdm-multirun
Project-URL: Documentation, https://pawamoy.github.io/pdm-multirun
Project-URL: Changelog, https://pawamoy.github.io/pdm-multirun/changelog
Project-URL: Repository, https://github.com/pawamoy/pdm-multirun
Project-URL: Issues, https://github.com/pawamoy/pdm-multirun/issues
Project-URL: Discussions, https://github.com/pawamoy/pdm-multirun/discussions
Project-URL: Gitter, https://gitter.im/pdm-multirun/community
Project-URL: Funding, https://github.com/sponsors/pawamoy
Requires-Python: >=3.8
Requires-Dist: pdm>=2
